eplier/__init__.py
eplier-0.0.1.dist-info/LICENSE
eplier-0.0.1.dist-info/METADATA
eplier-0.0.1.dist-info/WHEEL
eplier-0.0.1.dist-info/top_level.txt
eplier-0.0.1.dist-info/RECORD
