Metadata-Version: 2.1
Name: eplier
Version: 0.0.1
Classifier: Programming Language :: Python :: 3
Classifier: Operating System :: OS Independent
Requires-Python: >=3.7
License-File: LICENSE
Requires-Dist: pytorch
